transmission_cleaner/__init__.py
transmission_cleaner/actions.py
transmission_cleaner/client.py
transmission_cleaner/filters.py
transmission_cleaner/main.py
transmission_cleaner/checkers/__init__.py
transmission_cleaner/checkers/errors.py
transmission_cleaner/checkers/hardlinks.py
transmission_cleaner/checkers/orphans.py
transmission_cleaner-1.0.1.dist-info/licenses/LICENSE
transmission_cleaner-1.0.1.dist-info/METADATA
transmission_cleaner-1.0.1.dist-info/WHEEL
transmission_cleaner-1.0.1.dist-info/entry_points.txt
transmission_cleaner-1.0.1.dist-info/top_level.txt
transmission_cleaner-1.0.1.dist-info/RECORD
