Metadata-Version: 2.4
Name: transmission-cleaner
Version: 1.0.1
Summary: Transmission maintenance tool for managing torrents by hardlinks, errors, and orphaned files
Author-email: Your Name <flying_sausages@protonmail.com>
Maintainer-email: Your Name <flying_sausages@protonmail.com>
License-Expression: MIT
Project-URL: Homepage, https://github.com/flying-sausages/transmission-cleaner
Project-URL: Repository, https://github.com/flying-sausages/transmission-cleaner
Project-URL: Issues, https://github.com/flying-sausages/transmission-cleaner/issues
Keywords: transmission,torrent,hardlinks,cleanup,bittorrent
Classifier: Intended Audience :: End Users/Desktop
Classifier: Intended Audience :: System Administrators
Classifier: Operating System :: OS Independent
Classifier: Programming Language :: Python :: 3
Classifier: Programming Language :: Python :: 3.10
Classifier: Programming Language :: Python :: 3.11
Classifier: Programming Language :: Python :: 3.12
Classifier: Programming Language :: Python :: 3.13
Classifier: Programming Language :: Python :: 3.14
Classifier: Topic :: Communications :: File Sharing
Classifier: Topic :: System :: Filesystems
Classifier: Topic :: Utilities
Requires-Python: >=3.10
License-File: LICENSE
Requires-Dist: transmission-rpc>=7.0.11
Dynamic: license-file
